deckthehalls/__init__.py
deckthehalls/card.py
deckthehalls-0.1.0.dist-info/METADATA
deckthehalls-0.1.0.dist-info/WHEEL
deckthehalls-0.1.0.dist-info/entry_points.txt
deckthehalls-0.1.0.dist-info/licenses/LICENSE
deckthehalls-0.1.0.dist-info/RECORD
