Metadata-Version: 2.4
Name: deckthehalls
Version: 0.1.0
Summary: A festive terminal Christmas card for the Python community
Project-URL: Homepage, https://github.com/audreyfeldroy/deckthehalls
Project-URL: Repository, https://github.com/audreyfeldroy/deckthehalls
Author-email: Audrey and Daniel Roy Greenfeld <audrey@feldroy.com>
License-Expression: Apache-2.0
License-File: LICENSE
Keywords: christmas,holiday,python,terminal
Classifier: Development Status :: 3 - Alpha
Classifier: Environment :: Console
Classifier: Intended Audience :: Developers
Classifier: License :: OSI Approved :: Apache Software License
Classifier: Programming Language :: Python :: 3
Classifier: Programming Language :: Python :: 3.8
Classifier: Programming Language :: Python :: 3.9
Classifier: Programming Language :: Python :: 3.10
Classifier: Programming Language :: Python :: 3.11
Classifier: Programming Language :: Python :: 3.12
Classifier: Programming Language :: Python :: 3.13
Classifier: Topic :: Games/Entertainment
Requires-Python: >=3.8
Requires-Dist: rich>=13.0
